<?xml version="1.0" encoding="UTF-8"?>
<QCARConfig xmlns:xsi="http://www.w3.org/2001/XMLSchema-instance" xsi:noNamespaceSchemaLocation="qcar_config.xsd">
  <Tracking>
    <ImageTarget name="front_test_false" size="1.000000 0.531818" />
    <ImageTarget name="front_test_BW" size="1.000000 0.531775" />
    <ImageTarget name="Seite_Reduziert" size="0.297000 0.162300" />
    <ImageTarget name="Vorderseite_gray" size="0.100000 0.110279" />
    <ImageTarget name="Seite_5H" size="0.100000 0.063869" />
    <ImageTarget name="Seite_5G" size="0.100000 0.090791" />
    <ImageTarget name="Seite_5F" size="0.100000 0.090791" />
    <ImageTarget name="Seite_5E" size="0.100000 0.087065" />
    <ImageTarget name="Seite_5D" size="0.100000 0.084541" />
    <ImageTarget name="Seite_5C" size="0.100000 0.088050" />
    <ImageTarget name="Seite_5B" size="0.100000 0.073145" />
    <ImageTarget name="Seite_5A" size="0.100000 0.064103" />
    <ImageTarget name="Seite_4H" size="0.100000 0.063869" />
    <ImageTarget name="Seite_4G" size="0.100000 0.090791" />
    <ImageTarget name="Seite_4F" size="0.100000 0.090791" />
    <ImageTarget name="Seite_4E" size="0.100000 0.087065" />
    <ImageTarget name="Seite_4D" size="0.100000 0.084541" />
    <ImageTarget name="Seite_4C" size="0.100000 0.088050" />
    <ImageTarget name="Seite_4B" size="0.100000 0.073145" />
    <ImageTarget name="Seite_4A" size="0.100000 0.064103" />
    <ImageTarget name="Seite_3H" size="0.100000 0.063869" />
    <ImageTarget name="Seite_3G" size="0.100000 0.090791" />
    <ImageTarget name="Seite_3F" size="0.100000 0.090791" />
    <ImageTarget name="Seite_3E" size="0.100000 0.087065" />
    <ImageTarget name="Seite_3D" size="0.100000 0.084541" />
    <ImageTarget name="Seite_3C" size="0.100000 0.088050" />
    <ImageTarget name="Seite_3B" size="0.100000 0.073145" />
    <ImageTarget name="Seite_3A" size="0.100000 0.064103" />
    <ImageTarget name="Seite_2H" size="0.100000 0.063869" />
    <ImageTarget name="Seite_2G" size="0.100000 0.090791" />
    <ImageTarget name="Seite_2F" size="0.100000 0.090791" />
    <ImageTarget name="Seite_2E" size="0.100000 0.087065" />
    <ImageTarget name="Seite_2D" size="0.100000 0.084541" />
    <ImageTarget name="Seite_2C" size="0.100000 0.088050" />
    <ImageTarget name="Seite_2B" size="0.100000 0.073145" />
    <ImageTarget name="Seite_2A" size="0.100000 0.064103" />
    <ImageTarget name="Seite_1D" size="0.100000 0.110749" />
    <ImageTarget name="Seite_1C" size="0.100000 0.115346" />
    <ImageTarget name="Seite_1B" size="0.100000 0.095820" />
    <ImageTarget name="Seite_1A" size="0.100000 0.083974" />
    <ImageTarget name="Front_5E" size="0.046326 0.051145" />
    <ImageTarget name="Front_1C" size="0.046326 0.051098" />
    <ImageTarget name="Front_5D" size="0.046326 0.051098" />
    <ImageTarget name="Front_5C" size="0.046326 0.051098" />
    <ImageTarget name="Front_5B" size="0.046326 0.051098" />
    <ImageTarget name="Front_5A" size="0.046326 0.051098" />
    <ImageTarget name="Front_4E" size="0.046326 0.051145" />
    <ImageTarget name="Front_4D" size="0.046326 0.051098" />
    <ImageTarget name="Front_4C" size="0.046326 0.051098" />
    <ImageTarget name="Front_4B" size="0.046326 0.051098" />
    <ImageTarget name="Front_4A" size="0.046326 0.051098" />
    <ImageTarget name="Front_3E" size="0.046326 0.051145" />
    <ImageTarget name="Front_3D" size="0.046326 0.051098" />
    <ImageTarget name="Front_3C" size="0.046326 0.052576" />
    <ImageTarget name="Front_3B" size="0.046326 0.051098" />
    <ImageTarget name="Front_3A" size="0.046326 0.051098" />
    <ImageTarget name="Front_2D" size="0.046326 0.051056" />
    <ImageTarget name="Front_2C" size="0.046326 0.051098" />
    <ImageTarget name="Front_2B" size="0.046326 0.051098" />
  </Tracking>
</QCARConfig>
